rephorm/__init__.py
rephorm/decorators/__init__.py
rephorm/decorators/settings_validation.py
rephorm/dict/__init__.py
rephorm/dict/colors.py
rephorm/dict/legend_positions.py
rephorm/dict/styles.py
rephorm/dict/update_layout.py
rephorm/dict/update_traces.py
rephorm/object_mappers/__init__.py
rephorm/object_mappers/_globals.py
rephorm/object_mappers/chapter_mapper.py
rephorm/object_mappers/chart_mapper.py
rephorm/object_mappers/chart_series_mapper.py
rephorm/object_mappers/grid_mapper.py
rephorm/object_mappers/page_break_mapper.py
rephorm/object_mappers/report_mapper.py
rephorm/object_mappers/table_mapper.py
rephorm/object_mappers/table_section_mapper.py
rephorm/object_mappers/table_series_mapper.py
rephorm/object_mappers/text_mapper.py
rephorm/object_mappers/_utilities/__init__.py
rephorm/object_mappers/_utilities/chart_mapper_utility.py
rephorm/object_mappers/_utilities/grid_mapper_utility.py
rephorm/object_mappers/_utilities/table_mapper_utility.py
rephorm/object_params/__init__.py
rephorm/object_params/settings.py
rephorm/objects/__init__.py
rephorm/objects/chapter.py
rephorm/objects/chart.py
rephorm/objects/chart_series.py
rephorm/objects/footnote.py
rephorm/objects/grid.py
rephorm/objects/page_break.py
rephorm/objects/report.py
rephorm/objects/table.py
rephorm/objects/table_section.py
rephorm/objects/table_series.py
rephorm/objects/text.py
rephorm/objects/_utilities/__init__.py
rephorm/objects/_utilities/settings_container.py
rephorm/utility/PDF.py
rephorm/utility/__init__.py
rephorm/utility/add_style_prefix.py
rephorm/utility/is_set.py
rephorm/utility/unit_converter.py
rephorm/utility/fonts/OpenSans-Bold.ttf
rephorm/utility/fonts/OpenSans-BoldItalic.ttf
rephorm/utility/fonts/OpenSans-Italic.ttf
rephorm/utility/fonts/OpenSans.ttf
rephorm/utility/fonts/__init__.py
rephorm/utility/fonts/font_loading.py
rephorm/utility/merge/__init__.py
rephorm/utility/merge/chart_properties_manager.py
rephorm/utility/merge/merge_settings.py
rephorm/utility/merge/merge_styles.py
rephorm-1.1.2.dist-info/licenses/LICENSE
rephorm-1.1.2.dist-info/METADATA
rephorm-1.1.2.dist-info/WHEEL
rephorm-1.1.2.dist-info/top_level.txt
rephorm-1.1.2.dist-info/RECORD
