Metadata-Version: 2.4
Name: rephorm
Version: 1.1.2
Summary: Python package for generating PDF reports through code
Author-email: OGResearch <it@ogresearch.com>
Maintainer-email: Sergey Plotnikov <sergey.plotnikov@ogresearch.com>, Martynas Vycas <martynas.vycas@ogresearch.com>
License: MIT License
Classifier: Intended Audience :: Financial and Insurance Industry
Classifier: Programming Language :: Python :: 3
Classifier: Operating System :: OS Independent
Requires-Python: >=3.12
License-File: LICENSE
Requires-Dist: plotly==6.3.1
Requires-Dist: irispie>=0.68.1
Requires-Dist: fpdf2==2.8.4
Requires-Dist: PyMuPDF==1.25.1
Requires-Dist: twine==6.1.0
Requires-Dist: pkginfo==1.12.1.2
Requires-Dist: kaleido==1.1.0
Dynamic: license-file
